[
  {
    "question": "Почему контейнеры в default bridge сети не могут находить друг друга по имени?",
    "type": "single",
    "options": [
      { "text": "Default bridge не предоставляет встроенный DNS-сервер для резолвинга имён контейнеров", "correct": true },
      { "text": "Default bridge вообще не поддерживает сетевое взаимодействие", "correct": false, "explanation": "Default bridge поддерживает связь между контейнерами, но только по IP-адресам, а не по именам" },
      { "text": "Контейнеры в default bridge изолированы друг от друга", "correct": false, "explanation": "Контейнеры в default bridge видят друг друга по IP, но DNS по именам не работает. Для DNS нужна пользовательская сеть" },
      { "text": "Имена контейнеров не уникальны в default bridge", "correct": false, "explanation": "Имена контейнеров всегда уникальны. Проблема именно в отсутствии DNS-резолвинга в default bridge" }
    ]
  },
  {
    "question": "Какие преимущества даёт пользовательская bridge-сеть по сравнению с default bridge?",
    "type": "multiple",
    "options": [
      { "text": "Автоматический DNS — контейнеры находят друг друга по имени", "correct": true },
      { "text": "Изоляция — только участники сети видят друг друга", "correct": true },
      { "text": "Горячее подключение контейнеров через docker network connect", "correct": true },
      { "text": "Более высокая скорость передачи данных", "correct": false, "explanation": "Скорость передачи данных одинакова для default и пользовательских bridge-сетей. Преимущества в DNS, изоляции и управлении" }
    ]
  },
  {
    "question": "Чем EXPOSE в Dockerfile отличается от флага -p при docker run?",
    "type": "single",
    "options": [
      { "text": "EXPOSE — только документация, -p реально публикует порт на хосте", "correct": true },
      { "text": "EXPOSE автоматически публикует порт, -p переопределяет его", "correct": false, "explanation": "EXPOSE не публикует порт — это только метаданные. Для реальной публикации всегда нужен -p" },
      { "text": "Разницы нет — оба механизма делают одно и то же", "correct": false, "explanation": "Это принципиально разные вещи: EXPOSE — документация, -p — реальный проброс порта через iptables" },
      { "text": "EXPOSE работает для TCP, а -p — для UDP", "correct": false, "explanation": "Оба поддерживают и TCP, и UDP. Различие в назначении: EXPOSE документирует, -p публикует" }
    ]
  },
  {
    "question": "Почему не рекомендуется публиковать порты баз данных наружу?",
    "type": "single",
    "options": [
      { "text": "Это открывает базу данных для доступа из внешней сети, что является угрозой безопасности", "correct": true },
      { "text": "Docker не поддерживает проброс портов для баз данных", "correct": false, "explanation": "Docker поддерживает проброс любых портов. Но публикация портов БД — плохая практика с точки зрения безопасности" },
      { "text": "Это замедляет работу базы данных", "correct": false, "explanation": "Проброс порта не влияет на производительность. Проблема в безопасности: БД становится доступна извне" },
      { "text": "Порты баз данных конфликтуют с системными портами", "correct": false, "explanation": "Конфликт портов возможен, но главная причина — безопасность. БД должна быть доступна только внутри Docker-сети" }
    ]
  },
  {
    "question": "Как обеспечить связь между контейнерами из разных сетей?",
    "type": "single",
    "options": [
      { "text": "Подключить контейнер к обеим сетям через docker network connect", "correct": true },
      { "text": "Использовать флаг --link между контейнерами", "correct": false, "explanation": "--link устарел (deprecated). Правильный подход — использовать docker network connect для подключения к нескольким сетям" },
      { "text": "Контейнеры из разных сетей не могут общаться — это фундаментальное ограничение", "correct": false, "explanation": "Ограничение можно обойти: контейнер может быть подключён к нескольким сетям одновременно, выступая мостом" },
      { "text": "Использовать host network для всех контейнеров", "correct": false, "explanation": "Host network убирает всю сетевую изоляцию, что не рекомендуется. Правильный подход — docker network connect" }
    ]
  }
]
